ipgdrive/__init__.py
ipgdrive/_version.py
ipgdrive/cfg.py
ipgdrive/core.py
ipgdrive/job.py
ipgdrive/util.py
scripts/__init__.py
scripts/ipgdrive_cli.py
ipgdrive-0.0.12.dist-info/LICENSE
ipgdrive-0.0.12.dist-info/METADATA
ipgdrive-0.0.12.dist-info/WHEEL
ipgdrive-0.0.12.dist-info/entry_points.txt
ipgdrive-0.0.12.dist-info/top_level.txt
ipgdrive-0.0.12.dist-info/RECORD
