Metadata-Version: 2.1
Name: ipgdrive
Version: 0.0.12
Summary: Write host public ip to Google Drive.
Home-page: https://github.com/shaypal5/ipgdrive
Author: Shay Palachy
Author-email: shay.palachy@gmail.com
License: MIT
Platform: UNKNOWN
Classifier: Development Status :: 4 - Beta
Classifier: Intended Audience :: Developers
Classifier: Natural Language :: English
Classifier: License :: OSI Approved :: MIT License
Classifier: Programming Language :: Python
Classifier: Programming Language :: Python :: 3
Classifier: Programming Language :: Python :: 3.5
Classifier: Programming Language :: Python :: 3.6
Classifier: Programming Language :: Python :: 3.7
Classifier: Topic :: Software Development :: Libraries
Classifier: Topic :: Software Development :: Libraries :: Python Modules
Requires-Python: >=3.5
Requires-Dist: python-crontab
Requires-Dist: requests
Requires-Dist: birch
Requires-Dist: gspread
Requires-Dist: oauth2client
Requires-Dist: click
Provides-Extra: test
Requires-Dist: pytest ; extra == 'test'
Requires-Dist: coverage ; extra == 'test'
Requires-Dist: pytest-cov ; extra == 'test'
Requires-Dist: pyyaml ; extra == 'test'
Requires-Dist: collective.checkdocs ; extra == 'test'
Requires-Dist: pygments ; extra == 'test'
Requires-Dist: python-crontab ; extra == 'test'
Requires-Dist: requests ; extra == 'test'
Requires-Dist: birch ; extra == 'test'
Requires-Dist: gspread ; extra == 'test'
Requires-Dist: oauth2client ; extra == 'test'
Requires-Dist: click ; extra == 'test'
